dq_library/__init__.py
dq_library/config.py
dq_library/dq_checks.py
dq_library-0.1.0.dist-info/LICENSE
dq_library-0.1.0.dist-info/METADATA
dq_library-0.1.0.dist-info/WHEEL
dq_library-0.1.0.dist-info/top_level.txt
dq_library-0.1.0.dist-info/RECORD
